lzo_indexer/__init__.py
lzo_indexer/cli.py
lzo_indexer/indexer.py
python3_lzo_indexer-0.3.0.dist-info/METADATA
python3_lzo_indexer-0.3.0.dist-info/RECORD
python3_lzo_indexer-0.3.0.dist-info/WHEEL
python3_lzo_indexer-0.3.0.dist-info/entry_points.txt
python3_lzo_indexer-0.3.0.dist-info/top_level.txt
tests/__init__.py
tests/conftest.py
tests/test_indexer.py
