Metadata-Version: 2.1
Name: python3-lzo-indexer
Version: 0.3.0
Summary: Library for indexing LZO compressed files
Home-page: https://github.com/Orhideous/python3_lzo_indexer
Author: Tom Arnfeld
Author-email: tom@duedil.com
Maintainer: Andriy Kushnir (Orhideous)
Maintainer-email: me@orhideous.name
License: Apache Software License
Keywords: lzo,archive,indexing
Platform: UNKNOWN
Classifier: Development Status :: 4 - Beta
Classifier: Intended Audience :: Developers
Classifier: License :: OSI Approved :: Apache Software License
Classifier: Natural Language :: English
Classifier: Programming Language :: Python :: 3 :: Only
Classifier: Programming Language :: Python :: 3.6
Classifier: Programming Language :: Python :: 3.7
Requires-Dist: click (==7.0)
